RSA_Tools
