Metadata-Version: 1.1
Name: RSA-Tools
Version: 1.0.2
Summary: this is a test package for analysing RSA.
Home-page: http://www.ustc.edu.cn
Author: Chris New
Author-email: ncxhxgtg@mail.ustc.edu.cn
License: MIT
Keywords: RSA
Platform: UNKNOWN
Classifier: License :: OSI Approved :: MIT License
Classifier: Programming Language :: Python
Classifier: Intended Audience :: Developers
Classifier: Operating System :: OS Independent
